girder_sample_tracker/__init__.py
girder_sample_tracker/models/__init__.py
girder_sample_tracker/models/sample.py
girder_sample_tracker/rest/__init__.py
girder_sample_tracker/rest/sample.py
girder_sample_tracker/web_client/dist/girder-plugin-sample-tracker.umd.cjs
girder_sample_tracker/web_client/dist/style.css
girder_sample_tracker-2.0.5.dist-info/licenses/LICENSE
girder_sample_tracker-2.0.5.dist-info/METADATA
girder_sample_tracker-2.0.5.dist-info/WHEEL
girder_sample_tracker-2.0.5.dist-info/entry_points.txt
girder_sample_tracker-2.0.5.dist-info/top_level.txt
girder_sample_tracker-2.0.5.dist-info/RECORD
