Metadata-Version: 2.4
Name: girder-sample-tracker
Version: 2.0.5
Summary: Girder Plugin adding a simple tracker for material samples
License: BSD
Classifier: Development Status :: 4 - Beta
Classifier: Environment :: Web Environment
Classifier: License :: OSI Approved :: BSD License
Classifier: Operating System :: POSIX :: Linux
Classifier: Programming Language :: Python
Classifier: Programming Language :: Python :: 3
Requires-Python: >=3.10
License-File: LICENSE
Requires-Dist: girder>=5.0.0a5.dev0
Requires-Dist: qrcode[pil]
Requires-Dist: cairosvg
Dynamic: classifier
Dynamic: description
Dynamic: description-content-type
Dynamic: license
Dynamic: license-file
Dynamic: requires-dist
Dynamic: requires-python
Dynamic: summary
